{
  "generated_at": "2026-06-25 17:52:37",
  "exchange_rates": {
    "USD_TZS": {
      "current": 2627.3847,
      "next_1h": 2627.0323,
      "next_24h": 2620.0962,
      "change_pct": -0.013,
      "trend": "\ud83d\udcc9 DOWN",
      "predictions": [
        2627.0323,
        2626.6827,
        2626.3359,
        2625.9919,
        2625.6506,
        2625.312,
        2624.979,
        2624.6515,
        2624.3294,
        2624.0126,
        2623.7011,
        2623.3949,
        2623.0937,
        2622.7976,
        2622.5065,
        2622.2202,
        2621.9388,
        2621.662,
        2621.3899,
        2621.1224,
        2620.8593,
        2620.6006,
        2620.3463,
        2620.0962
      ],
      "metrics": {
        "MAE": 0.576573,
        "RMSE": 2.554674,
        "MAPE": 0.022,
        "R2": 0.858
      }
    },
    "USD_KES": {
      "current": 129.4177,
      "next_1h": 129.4176,
      "next_24h": 129.415,
      "change_pct": 0.0,
      "trend": "\ud83d\udcc9 DOWN",
      "predictions": [
        129.4176,
        129.4174,
        129.4173,
        129.4172,
        129.4171,
        129.4169,
        129.4168,
        129.4167,
        129.4166,
        129.4165,
        129.4164,
        129.4162,
        129.4161,
        129.416,
        129.4159,
        129.4158,
        129.4157,
        129.4156,
        129.4155,
        129.4154,
        129.4153,
        129.4152,
        129.4151,
        129.415
      ],
      "metrics": {
        "MAE": 0.003278,
        "RMSE": 0.015258,
        "MAPE": 0.0025,
        "R2": 0.8626
      }
    },
    "USD_UGX": {
      "current": 3651.2094,
      "next_1h": 3652.9315,
      "next_24h": 3685.9187,
      "change_pct": 0.047,
      "trend": "\ud83d\udcc8 UP",
      "predictions": [
        3652.9315,
        3654.6402,
        3656.3358,
        3658.0185,
        3659.6885,
        3661.3458,
        3662.9697,
        3664.5604,
        3666.1184,
        3667.6442,
        3669.1381,
        3670.6005,
        3672.032,
        3673.4334,
        3674.8052,
        3676.148,
        3677.4625,
        3678.7492,
        3680.0087,
        3681.2417,
        3682.4486,
        3683.6301,
        3684.7866,
        3685.9187
      ],
      "metrics": {
        "MAE": 2.727091,
        "RMSE": 5.710946,
        "MAPE": 0.0747,
        "R2": 0.8991
      }
    },
    "USD_EUR": {
      "current": 0.8808,
      "next_1h": 0.8806,
      "next_24h": 0.8765,
      "change_pct": -0.024,
      "trend": "\ud83d\udcc9 DOWN",
      "predictions": [
        0.8806,
        0.8804,
        0.8802,
        0.88,
        0.8798,
        0.8796,
        0.8794,
        0.8792,
        0.879,
        0.8789,
        0.8787,
        0.8785,
        0.8783,
        0.8781,
        0.878,
        0.8778,
        0.8776,
        0.8775,
        0.8773,
        0.8771,
        0.877,
        0.8768,
        0.8766,
        0.8765
      ],
      "metrics": {
        "MAE": 0.00025,
        "RMSE": 0.00079,
        "MAPE": 0.0286,
        "R2": 0.9792
      }
    }
  },
  "crypto": {
    "BTC_USD": {
      "current": 59407.0,
      "next_1h": 59321.31,
      "next_24h": 59276.38,
      "change_pct": -0.144,
      "trend": "\ud83d\udcc9 DOWN",
      "predictions": [
        59321.31,
        59160.23,
        59163.32,
        59189.74,
        59204.21,
        59192.96,
        59184.37,
        59192.12,
        59200.17,
        59205.17,
        59208.4,
        59212.8,
        59218.62,
        59224.17,
        59229.32,
        59234.4,
        59239.66,
        59245.0,
        59250.28,
        59255.5,
        59260.72,
        59265.95,
        59271.17,
        59276.38
      ],
      "metrics": {
        "MAE": 255.12963,
        "RMSE": 387.345923,
        "MAPE": 0.406,
        "R2": 0.935
      }
    },
    "ETH_USD": {
      "current": 1566.51,
      "next_1h": 1564.32,
      "next_24h": 1574.15,
      "change_pct": -0.14,
      "trend": "\ud83d\udcc9 DOWN",
      "predictions": [
        1564.32,
        1565.56,
        1566.64,
        1567.09,
        1567.21,
        1567.7,
        1568.08,
        1568.42,
        1568.78,
        1569.16,
        1569.52,
        1569.88,
        1570.24,
        1570.6,
        1570.96,
        1571.32,
        1571.68,
        1572.03,
        1572.39,
        1572.74,
        1573.1,
        1573.45,
        1573.8,
        1574.15
      ],
      "metrics": {
        "MAE": 8.676726,
        "RMSE": 13.455482,
        "MAPE": 0.5129,
        "R2": 0.9366
      }
    },
    "BNB_USD": {
      "current": 556.92,
      "next_1h": 556.7,
      "next_24h": 566.69,
      "change_pct": -0.039,
      "trend": "\ud83d\udcc9 DOWN",
      "predictions": [
        556.7,
        557.18,
        557.87,
        558.47,
        558.85,
        559.3,
        559.75,
        560.19,
        560.61,
        561.04,
        561.46,
        561.88,
        562.29,
        562.71,
        563.12,
        563.53,
        563.93,
        564.33,
        564.73,
        565.13,
        565.52,
        565.91,
        566.3,
        566.69
      ],
      "metrics": {
        "MAE": 2.110181,
        "RMSE": 3.208919,
        "MAPE": 0.3637,
        "R2": 0.943
      }
    }
  }
}