{
  "generated_at": "2026-06-29 05:46:48",
  "exchange_rates": {
    "USD_TZS": {
      "current": 2630.0296,
      "next_1h": 2629.6436,
      "next_24h": 2621.9411,
      "change_pct": -0.015,
      "trend": "\ud83d\udcc9 DOWN",
      "predictions": [
        2629.6436,
        2629.2616,
        2628.8837,
        2628.4879,
        2628.0963,
        2627.7087,
        2627.3288,
        2626.9564,
        2626.5914,
        2626.2339,
        2625.8838,
        2625.5409,
        2625.2051,
        2624.8763,
        2624.5543,
        2624.239,
        2623.9302,
        2623.6279,
        2623.3318,
        2623.0419,
        2622.758,
        2622.48,
        2622.2077,
        2621.9411
      ],
      "metrics": {
        "MAE": 0.671572,
        "RMSE": 2.990111,
        "MAPE": 0.0256,
        "R2": 0.8803
      }
    },
    "USD_KES": {
      "current": 129.524,
      "next_1h": 129.5226,
      "next_24h": 129.4957,
      "change_pct": -0.001,
      "trend": "\ud83d\udcc9 DOWN",
      "predictions": [
        129.5226,
        129.5212,
        129.5198,
        129.5184,
        129.5171,
        129.5158,
        129.5146,
        129.5133,
        129.5121,
        129.5109,
        129.5097,
        129.5085,
        129.5073,
        129.5062,
        129.5051,
        129.504,
        129.5029,
        129.5018,
        129.5007,
        129.4997,
        129.4987,
        129.4976,
        129.4966,
        129.4957
      ],
      "metrics": {
        "MAE": 0.003421,
        "RMSE": 0.015307,
        "MAPE": 0.0026,
        "R2": 0.9233
      }
    },
    "USD_UGX": {
      "current": 3661.4265,
      "next_1h": 3661.6772,
      "next_24h": 3667.0345,
      "change_pct": 0.007,
      "trend": "\ud83d\udcc8 UP",
      "predictions": [
        3661.6772,
        3661.9274,
        3662.1771,
        3662.4184,
        3662.6592,
        3662.8996,
        3663.1388,
        3663.3769,
        3663.6138,
        3663.8496,
        3664.0842,
        3664.3178,
        3664.5502,
        3664.7815,
        3665.0117,
        3665.2408,
        3665.4688,
        3665.6957,
        3665.9215,
        3666.1462,
        3666.3699,
        3666.5925,
        3666.8141,
        3667.0345
      ],
      "metrics": {
        "MAE": 0.98722,
        "RMSE": 3.759665,
        "MAPE": 0.027,
        "R2": 0.9141
      }
    },
    "USD_EUR": {
      "current": 0.8782,
      "next_1h": 0.8782,
      "next_24h": 0.8769,
      "change_pct": -0.007,
      "trend": "\ud83d\udcc9 DOWN",
      "predictions": [
        0.8782,
        0.8781,
        0.8781,
        0.878,
        0.8779,
        0.8779,
        0.8778,
        0.8778,
        0.8777,
        0.8776,
        0.8776,
        0.8775,
        0.8775,
        0.8774,
        0.8774,
        0.8773,
        0.8772,
        0.8772,
        0.8771,
        0.8771,
        0.877,
        0.877,
        0.8769,
        0.8769
      ],
      "metrics": {
        "MAE": 0.000136,
        "RMSE": 0.000482,
        "MAPE": 0.0155,
        "R2": 0.977
      }
    }
  },
  "crypto": {
    "BTC_USD": {
      "current": 59816.0,
      "next_1h": 59737.9,
      "next_24h": 59742.55,
      "change_pct": -0.131,
      "trend": "\ud83d\udcc9 DOWN",
      "predictions": [
        59737.9,
        59759.7,
        59772.36,
        59811.82,
        59792.58,
        59780.99,
        59782.28,
        59782.61,
        59782.61,
        59778.1,
        59774.69,
        59772.69,
        59770.48,
        59768.02,
        59765.25,
        59762.64,
        59760.17,
        59757.67,
        59755.13,
        59752.59,
        59750.07,
        59747.56,
        59745.06,
        59742.55
      ],
      "metrics": {
        "MAE": 239.934111,
        "RMSE": 364.267423,
        "MAPE": 0.3923,
        "R2": 0.9612
      }
    },
    "ETH_USD": {
      "current": 1575.99,
      "next_1h": 1575.49,
      "next_24h": 1580.3,
      "change_pct": -0.032,
      "trend": "\ud83d\udcc9 DOWN",
      "predictions": [
        1575.49,
        1576.06,
        1576.99,
        1576.54,
        1576.8,
        1577.05,
        1577.26,
        1577.4,
        1577.6,
        1577.78,
        1577.97,
        1578.15,
        1578.33,
        1578.51,
        1578.69,
        1578.88,
        1579.06,
        1579.24,
        1579.41,
        1579.59,
        1579.77,
        1579.95,
        1580.12,
        1580.3
      ],
      "metrics": {
        "MAE": 7.754432,
        "RMSE": 12.287431,
        "MAPE": 0.4775,
        "R2": 0.9673
      }
    },
    "BNB_USD": {
      "current": 550.61,
      "next_1h": 551.11,
      "next_24h": 558.4,
      "change_pct": 0.091,
      "trend": "\ud83d\udcc8 UP",
      "predictions": [
        551.11,
        551.68,
        552.02,
        552.11,
        552.47,
        552.82,
        553.13,
        553.45,
        553.77,
        554.1,
        554.41,
        554.73,
        555.05,
        555.36,
        555.67,
        555.98,
        556.29,
        556.6,
        556.9,
        557.21,
        557.51,
        557.8,
        558.1,
        558.4
      ],
      "metrics": {
        "MAE": 2.021876,
        "RMSE": 3.011421,
        "MAPE": 0.3562,
        "R2": 0.9533
      }
    }
  }
}