{
  "generated_at": "2026-07-13 22:17:11",
  "exchange_rates": {
    "USD_TZS": {
      "current": 2627.8658,
      "next_1h": 2627.4802,
      "next_24h": 2621.0728,
      "change_pct": -0.015,
      "trend": "\ud83d\udcc9 DOWN",
      "predictions": [
        2627.4802,
        2627.1031,
        2626.7341,
        2626.3732,
        2626.0201,
        2625.6748,
        2625.3405,
        2625.0171,
        2624.7042,
        2624.4015,
        2624.1087,
        2623.8255,
        2623.5516,
        2623.2868,
        2623.0306,
        2622.7829,
        2622.5433,
        2622.3116,
        2622.0875,
        2621.8708,
        2621.6612,
        2621.4585,
        2621.2624,
        2621.0728
      ],
      "metrics": {
        "MAE": 0.386875,
        "RMSE": 0.659724,
        "MAPE": 0.0147,
        "R2": 0.8442
      }
    },
    "USD_KES": {
      "current": 129.1822,
      "next_1h": 129.1856,
      "next_24h": 129.2538,
      "change_pct": 0.003,
      "trend": "\ud83d\udcc8 UP",
      "predictions": [
        129.1856,
        129.189,
        129.1923,
        129.1957,
        129.199,
        129.2023,
        129.2055,
        129.2087,
        129.2119,
        129.215,
        129.2181,
        129.2211,
        129.224,
        129.227,
        129.2298,
        129.2327,
        129.2355,
        129.2382,
        129.2409,
        129.2436,
        129.2462,
        129.2488,
        129.2513,
        129.2538
      ],
      "metrics": {
        "MAE": 0.005098,
        "RMSE": 0.013746,
        "MAPE": 0.0039,
        "R2": 0.8782
      }
    },
    "USD_UGX": {
      "current": 3659.3418,
      "next_1h": 3659.3039,
      "next_24h": 3658.4525,
      "change_pct": -0.001,
      "trend": "\ud83d\udcc9 DOWN",
      "predictions": [
        3659.3039,
        3659.266,
        3659.2282,
        3659.1905,
        3659.1529,
        3659.1153,
        3659.0778,
        3659.0404,
        3659.003,
        3658.9658,
        3658.9286,
        3658.8915,
        3658.8545,
        3658.8175,
        3658.7807,
        3658.7439,
        3658.7072,
        3658.6706,
        3658.634,
        3658.5976,
        3658.5612,
        3658.5249,
        3658.4887,
        3658.4525
      ],
      "metrics": {
        "MAE": 0.61522,
        "RMSE": 3.191407,
        "MAPE": 0.0168,
        "R2": 0.898
      }
    },
    "USD_EUR": {
      "current": 0.8768,
      "next_1h": 0.8768,
      "next_24h": 0.8768,
      "change_pct": 0.0,
      "trend": "\ud83d\udcc9 DOWN",
      "predictions": [
        0.8768,
        0.8768,
        0.8768,
        0.8768,
        0.8768,
        0.8768,
        0.8768,
        0.8768,
        0.8768,
        0.8768,
        0.8768,
        0.8768,
        0.8768,
        0.8768,
        0.8768,
        0.8768,
        0.8768,
        0.8768,
        0.8768,
        0.8768,
        0.8768,
        0.8768,
        0.8768,
        0.8768
      ],
      "metrics": {
        "MAE": 3.2e-05,
        "RMSE": 0.000177,
        "MAPE": 0.0037,
        "R2": 0.9404
      }
    }
  },
  "crypto": {
    "BTC_USD": {
      "current": 62121.0,
      "next_1h": 62132.34,
      "next_24h": 62044.01,
      "change_pct": 0.018,
      "trend": "\ud83d\udcc8 UP",
      "predictions": [
        62132.34,
        62115.65,
        62095.27,
        62092.55,
        62098.84,
        62096.48,
        62092.2,
        62088.44,
        62085.78,
        62083.26,
        62080.38,
        62077.43,
        62074.54,
        62071.72,
        62068.9,
        62066.09,
        62063.28,
        62060.49,
        62057.71,
        62054.95,
        62052.19,
        62049.45,
        62046.72,
        62044.01
      ],
      "metrics": {
        "MAE": 93.161265,
        "RMSE": 128.514417,
        "MAPE": 0.1467,
        "R2": 0.9611
      }
    },
    "ETH_USD": {
      "current": 1764.35,
      "next_1h": 1764.21,
      "next_24h": 1754.59,
      "change_pct": -0.008,
      "trend": "\ud83d\udcc9 DOWN",
      "predictions": [
        1764.21,
        1763.14,
        1762.57,
        1762.58,
        1761.96,
        1761.52,
        1761.13,
        1760.74,
        1760.33,
        1759.94,
        1759.54,
        1759.15,
        1758.76,
        1758.37,
        1757.98,
        1757.6,
        1757.21,
        1756.83,
        1756.45,
        1756.08,
        1755.7,
        1755.33,
        1754.96,
        1754.59
      ],
      "metrics": {
        "MAE": 3.837721,
        "RMSE": 5.862997,
        "MAPE": 0.2144,
        "R2": 0.9346
      }
    },
    "BNB_USD": {
      "current": 565.56,
      "next_1h": 565.6,
      "next_24h": 566.73,
      "change_pct": 0.007,
      "trend": "\ud83d\udcc8 UP",
      "predictions": [
        565.6,
        565.61,
        565.64,
        565.76,
        565.8,
        565.85,
        565.9,
        565.95,
        566.0,
        566.05,
        566.1,
        566.15,
        566.2,
        566.25,
        566.3,
        566.35,
        566.39,
        566.44,
        566.49,
        566.54,
        566.59,
        566.63,
        566.68,
        566.73
      ],
      "metrics": {
        "MAE": 0.790274,
        "RMSE": 1.14999,
        "MAPE": 0.1378,
        "R2": 0.9344
      }
    }
  }
}