{
  "generated_at": "2026-07-22 19:43:17",
  "exchange_rates": {
    "USD_TZS": {
      "current": 2628.1023,
      "next_1h": 2627.8236,
      "next_24h": 2623.0001,
      "change_pct": -0.011,
      "trend": "\ud83d\udcc9 DOWN",
      "predictions": [
        2627.8236,
        2627.5503,
        2627.2822,
        2627.0192,
        2626.7614,
        2626.5085,
        2626.2626,
        2626.0237,
        2625.7914,
        2625.5656,
        2625.3463,
        2625.1331,
        2624.926,
        2624.7247,
        2624.5291,
        2624.3391,
        2624.1544,
        2623.975,
        2623.8006,
        2623.6312,
        2623.4666,
        2623.3066,
        2623.1511,
        2623.0001
      ],
      "metrics": {
        "MAE": 0.515689,
        "RMSE": 2.019583,
        "MAPE": 0.0197,
        "R2": 0.9582
      }
    },
    "USD_KES": {
      "current": 129.3824,
      "next_1h": 129.3822,
      "next_24h": 129.3777,
      "change_pct": 0.0,
      "trend": "\ud83d\udcc9 DOWN",
      "predictions": [
        129.3822,
        129.382,
        129.3818,
        129.3816,
        129.3814,
        129.3812,
        129.3809,
        129.3807,
        129.3805,
        129.3803,
        129.3801,
        129.3799,
        129.3797,
        129.3795,
        129.3793,
        129.3792,
        129.379,
        129.3788,
        129.3786,
        129.3784,
        129.3782,
        129.378,
        129.3779,
        129.3777
      ],
      "metrics": {
        "MAE": 0.00262,
        "RMSE": 0.013156,
        "MAPE": 0.002,
        "R2": 0.9182
      }
    },
    "USD_UGX": {
      "current": 3692.4788,
      "next_1h": 3692.4109,
      "next_24h": 3690.901,
      "change_pct": -0.002,
      "trend": "\ud83d\udcc9 DOWN",
      "predictions": [
        3692.4109,
        3692.343,
        3692.2754,
        3692.2078,
        3692.1405,
        3692.0732,
        3692.0062,
        3691.9394,
        3691.8729,
        3691.8065,
        3691.7404,
        3691.6745,
        3691.6089,
        3691.5434,
        3691.4782,
        3691.4132,
        3691.3484,
        3691.2839,
        3691.2195,
        3691.1554,
        3691.0915,
        3691.0278,
        3690.9643,
        3690.901
      ],
      "metrics": {
        "MAE": 0.430554,
        "RMSE": 2.396886,
        "MAPE": 0.0117,
        "R2": 0.955
      }
    },
    "USD_EUR": {
      "current": 0.8767,
      "next_1h": 0.8767,
      "next_24h": 0.8768,
      "change_pct": 0.001,
      "trend": "\ud83d\udcc8 UP",
      "predictions": [
        0.8767,
        0.8767,
        0.8767,
        0.8767,
        0.8767,
        0.8767,
        0.8767,
        0.8767,
        0.8767,
        0.8767,
        0.8767,
        0.8767,
        0.8767,
        0.8768,
        0.8768,
        0.8768,
        0.8768,
        0.8768,
        0.8768,
        0.8768,
        0.8768,
        0.8768,
        0.8768,
        0.8768
      ],
      "metrics": {
        "MAE": 4.2e-05,
        "RMSE": 0.000225,
        "MAPE": 0.0048,
        "R2": 0.9699
      }
    }
  },
  "crypto": {
    "BTC_USD": {
      "current": 65859.0,
      "next_1h": 65843.4,
      "next_24h": 65483.49,
      "change_pct": -0.024,
      "trend": "\ud83d\udcc9 DOWN",
      "predictions": [
        65843.4,
        65810.92,
        65783.9,
        65772.53,
        65762.87,
        65747.45,
        65731.02,
        65715.35,
        65700.59,
        65685.88,
        65670.94,
        65656.02,
        65641.23,
        65626.56,
        65611.95,
        65597.39,
        65582.91,
        65568.49,
        65554.15,
        65539.88,
        65525.68,
        65511.55,
        65497.48,
        65483.49
      ],
      "metrics": {
        "MAE": 98.696491,
        "RMSE": 144.343905,
        "MAPE": 0.1524,
        "R2": 0.9794
      }
    },
    "ETH_USD": {
      "current": 1925.72,
      "next_1h": 1924.74,
      "next_24h": 1904.95,
      "change_pct": -0.051,
      "trend": "\ud83d\udcc9 DOWN",
      "predictions": [
        1924.74,
        1923.68,
        1922.89,
        1922.0,
        1921.08,
        1920.19,
        1919.31,
        1918.43,
        1917.56,
        1916.69,
        1915.82,
        1914.96,
        1914.1,
        1913.25,
        1912.4,
        1911.56,
        1910.72,
        1909.88,
        1909.05,
        1908.22,
        1907.4,
        1906.58,
        1905.76,
        1904.95
      ],
      "metrics": {
        "MAE": 3.956064,
        "RMSE": 5.536423,
        "MAPE": 0.2103,
        "R2": 0.9759
      }
    },
    "BNB_USD": {
      "current": 569.5,
      "next_1h": 569.55,
      "next_24h": 570.47,
      "change_pct": 0.008,
      "trend": "\ud83d\udcc8 UP",
      "predictions": [
        569.55,
        569.56,
        569.6,
        569.65,
        569.7,
        569.74,
        569.78,
        569.82,
        569.86,
        569.91,
        569.95,
        569.99,
        570.03,
        570.07,
        570.11,
        570.15,
        570.19,
        570.23,
        570.27,
        570.31,
        570.35,
        570.39,
        570.43,
        570.47
      ],
      "metrics": {
        "MAE": 0.758874,
        "RMSE": 1.053516,
        "MAPE": 0.1332,
        "R2": 0.9168
      }
    }
  }
}