{
  "generated_at": "2026-06-20 03:19:58",
  "exchange_rates": {
    "USD_TZS": {
      "current": 2612.1229,
      "next_1h": 2611.9553,
      "next_24h": 2609.8905,
      "change_pct": -0.006,
      "trend": "\ud83d\udcc9 DOWN",
      "predictions": [
        2611.9553,
        2611.7887,
        2611.6232,
        2611.4586,
        2611.3686,
        2611.2791,
        2611.1914,
        2611.1053,
        2611.0208,
        2610.9381,
        2610.8564,
        2610.7759,
        2610.6965,
        2610.6181,
        2610.5408,
        2610.4646,
        2610.3893,
        2610.3151,
        2610.2419,
        2610.1697,
        2610.0985,
        2610.0282,
        2609.9589,
        2609.8905
      ],
      "metrics": {
        "MAE": 0.667777,
        "RMSE": 3.090449,
        "MAPE": 0.0256,
        "R2": 0.8117
      }
    },
    "USD_KES": {
      "current": 129.459,
      "next_1h": 129.4582,
      "next_24h": 129.4417,
      "change_pct": -0.001,
      "trend": "\ud83d\udcc9 DOWN",
      "predictions": [
        129.4582,
        129.4574,
        129.4566,
        129.4558,
        129.455,
        129.4543,
        129.4535,
        129.4528,
        129.452,
        129.4513,
        129.4506,
        129.4499,
        129.4491,
        129.4484,
        129.4477,
        129.447,
        129.4463,
        129.4457,
        129.445,
        129.4443,
        129.4436,
        129.443,
        129.4423,
        129.4417
      ],
      "metrics": {
        "MAE": 0.003178,
        "RMSE": 0.014344,
        "MAPE": 0.0025,
        "R2": 0.8987
      }
    },
    "USD_UGX": {
      "current": 3669.712,
      "next_1h": 3671.3224,
      "next_24h": 3696.1279,
      "change_pct": 0.044,
      "trend": "\ud83d\udcc8 UP",
      "predictions": [
        3671.3224,
        3672.9186,
        3674.501,
        3676.0695,
        3677.2605,
        3678.4412,
        3679.597,
        3680.7284,
        3681.8356,
        3682.9191,
        3683.9824,
        3685.0258,
        3686.0497,
        3687.0544,
        3688.0404,
        3689.0081,
        3689.9577,
        3690.8896,
        3691.8042,
        3692.7018,
        3693.5826,
        3694.447,
        3695.2954,
        3696.1279
      ],
      "metrics": {
        "MAE": 1.936423,
        "RMSE": 6.189551,
        "MAPE": 0.0526,
        "R2": 0.9762
      }
    },
    "USD_EUR": {
      "current": 0.8719,
      "next_1h": 0.8719,
      "next_24h": 0.8716,
      "change_pct": -0.002,
      "trend": "\ud83d\udcc9 DOWN",
      "predictions": [
        0.8719,
        0.8719,
        0.8719,
        0.8719,
        0.8719,
        0.8718,
        0.8718,
        0.8718,
        0.8718,
        0.8718,
        0.8718,
        0.8718,
        0.8717,
        0.8717,
        0.8717,
        0.8717,
        0.8717,
        0.8717,
        0.8717,
        0.8717,
        0.8716,
        0.8716,
        0.8716,
        0.8716
      ],
      "metrics": {
        "MAE": 0.000128,
        "RMSE": 0.000665,
        "MAPE": 0.0147,
        "R2": 0.9456
      }
    }
  },
  "crypto": {
    "BTC_USD": {
      "current": 63344.0,
      "next_1h": 63301.1,
      "next_24h": 62210.95,
      "change_pct": -0.068,
      "trend": "\ud83d\udcc9 DOWN",
      "predictions": [
        63301.1,
        63269.16,
        63235.91,
        63198.11,
        63147.74,
        63099.42,
        63052.58,
        63005.01,
        62956.23,
        62906.77,
        62857.6,
        62808.47,
        62759.12,
        62709.59,
        62660.0,
        62610.38,
        62560.69,
        62510.92,
        62461.08,
        62411.18,
        62361.22,
        62311.2,
        62261.11,
        62210.95
      ],
      "metrics": {
        "MAE": 244.737854,
        "RMSE": 342.82098,
        "MAPE": 0.3812,
        "R2": 0.9283
      }
    },
    "ETH_USD": {
      "current": 1706.5,
      "next_1h": 1705.2,
      "next_24h": 1672.26,
      "change_pct": -0.076,
      "trend": "\ud83d\udcc9 DOWN",
      "predictions": [
        1705.2,
        1703.84,
        1702.54,
        1701.19,
        1699.76,
        1698.32,
        1696.89,
        1695.45,
        1694.01,
        1692.56,
        1691.12,
        1689.67,
        1688.23,
        1686.78,
        1685.33,
        1683.88,
        1682.43,
        1680.98,
        1679.53,
        1678.08,
        1676.62,
        1675.17,
        1673.72,
        1672.26
      ],
      "metrics": {
        "MAE": 8.816674,
        "RMSE": 13.822601,
        "MAPE": 0.5116,
        "R2": 0.9277
      }
    },
    "BNB_USD": {
      "current": 580.12,
      "next_1h": 580.36,
      "next_24h": 585.11,
      "change_pct": 0.041,
      "trend": "\ud83d\udcc8 UP",
      "predictions": [
        580.36,
        580.56,
        580.74,
        580.93,
        581.15,
        581.36,
        581.58,
        581.79,
        582.01,
        582.22,
        582.43,
        582.64,
        582.86,
        583.07,
        583.28,
        583.48,
        583.69,
        583.9,
        584.1,
        584.3,
        584.51,
        584.71,
        584.91,
        585.11
      ],
      "metrics": {
        "MAE": 2.07942,
        "RMSE": 2.975536,
        "MAPE": 0.3464,
        "R2": 0.946
      }
    }
  }
}