{
  "generated_at": "2026-05-20 20:51:51",
  "exchange_rates": {
    "USD_TZS": {
      "current": 2572.1034,
      "next_1h": 2574.0047,
      "next_24h": 2597.5758,
      "change_pct": 0.074,
      "trend": "\ud83d\udcc8 UP",
      "predictions": [
        2574.0047,
        2575.8452,
        2577.6268,
        2579.3514,
        2581.0208,
        2582.6368,
        2584.1403,
        2585.537,
        2586.832,
        2588.0306,
        2589.1374,
        2590.1572,
        2591.0963,
        2591.9608,
        2592.7563,
        2593.488,
        2594.1609,
        2594.7797,
        2595.3488,
        2595.872,
        2596.353,
        2596.7953,
        2597.202,
        2597.5758
      ],
      "metrics": {
        "MAE": 0.83301,
        "RMSE": 2.3641,
        "MAPE": 0.0322,
        "R2": 0.9434
      }
    },
    "USD_KES": {
      "current": 129.4148,
      "next_1h": 129.4088,
      "next_24h": 129.2996,
      "change_pct": -0.005,
      "trend": "\ud83d\udcc9 DOWN",
      "predictions": [
        129.4088,
        129.4029,
        129.3971,
        129.3914,
        129.3857,
        129.3801,
        129.3747,
        129.3694,
        129.3642,
        129.3591,
        129.3542,
        129.3493,
        129.3446,
        129.34,
        129.3355,
        129.3311,
        129.3268,
        129.3227,
        129.3186,
        129.3146,
        129.3107,
        129.3069,
        129.3032,
        129.2996
      ],
      "metrics": {
        "MAE": 0.005132,
        "RMSE": 0.01908,
        "MAPE": 0.004,
        "R2": 0.947
      }
    },
    "USD_UGX": {
      "current": 3733.9743,
      "next_1h": 3733.6934,
      "next_24h": 3727.9136,
      "change_pct": -0.008,
      "trend": "\ud83d\udcc9 DOWN",
      "predictions": [
        3733.6934,
        3733.414,
        3733.1363,
        3732.8601,
        3732.5854,
        3732.3123,
        3732.0424,
        3731.7757,
        3731.5121,
        3731.2517,
        3730.9943,
        3730.7399,
        3730.4886,
        3730.2403,
        3729.9949,
        3729.7524,
        3729.5128,
        3729.2761,
        3729.0422,
        3728.811,
        3728.5826,
        3728.357,
        3728.134,
        3727.9136
      ],
      "metrics": {
        "MAE": 0.465101,
        "RMSE": 1.50581,
        "MAPE": 0.0125,
        "R2": 0.9112
      }
    },
    "USD_EUR": {
      "current": 0.8612,
      "next_1h": 0.8611,
      "next_24h": 0.8586,
      "change_pct": -0.014,
      "trend": "\ud83d\udcc9 DOWN",
      "predictions": [
        0.8611,
        0.861,
        0.8608,
        0.8607,
        0.8606,
        0.8605,
        0.8604,
        0.8602,
        0.8601,
        0.86,
        0.8599,
        0.8598,
        0.8597,
        0.8596,
        0.8595,
        0.8594,
        0.8593,
        0.8592,
        0.8591,
        0.859,
        0.8589,
        0.8588,
        0.8587,
        0.8586
      ],
      "metrics": {
        "MAE": 0.000181,
        "RMSE": 0.000547,
        "MAPE": 0.0211,
        "R2": 0.9741
      }
    }
  },
  "crypto": {
    "BTC_USD": {
      "current": 77647.0,
      "next_1h": 77649.53,
      "next_24h": 77926.72,
      "change_pct": 0.003,
      "trend": "\ud83d\udcc8 UP",
      "predictions": [
        77649.53,
        77659.61,
        77668.67,
        77677.04,
        77689.85,
        77703.75,
        77717.14,
        77730.43,
        77743.53,
        77756.42,
        77769.2,
        77781.9,
        77794.5,
        77807.0,
        77819.41,
        77831.71,
        77843.92,
        77856.04,
        77868.05,
        77879.97,
        77891.8,
        77903.53,
        77915.18,
        77926.72
      ],
      "metrics": {
        "MAE": 189.165295,
        "RMSE": 264.746085,
        "MAPE": 0.2402,
        "R2": 0.9684
      }
    },
    "ETH_USD": {
      "current": 2134.19,
      "next_1h": 2141.64,
      "next_24h": 2254.9,
      "change_pct": 0.349,
      "trend": "\ud83d\udcc8 UP",
      "predictions": [
        2141.64,
        2149.55,
        2156.27,
        2163.45,
        2169.86,
        2176.17,
        2182.28,
        2188.09,
        2193.7,
        2199.07,
        2204.22,
        2209.16,
        2213.9,
        2218.44,
        2222.81,
        2226.99,
        2231.01,
        2234.86,
        2238.56,
        2242.1,
        2245.5,
        2248.77,
        2251.9,
        2254.9
      ],
      "metrics": {
        "MAE": 8.728909,
        "RMSE": 12.07425,
        "MAPE": 0.3992,
        "R2": 0.9647
      }
    },
    "BNB_USD": {
      "current": 650.5,
      "next_1h": 650.2,
      "next_24h": 648.23,
      "change_pct": -0.046,
      "trend": "\ud83d\udcc9 DOWN",
      "predictions": [
        650.2,
        650.05,
        649.98,
        649.86,
        649.76,
        649.67,
        649.59,
        649.5,
        649.42,
        649.33,
        649.25,
        649.17,
        649.08,
        649.0,
        648.92,
        648.84,
        648.76,
        648.69,
        648.61,
        648.53,
        648.46,
        648.38,
        648.31,
        648.23
      ],
      "metrics": {
        "MAE": 1.896909,
        "RMSE": 2.652177,
        "MAPE": 0.2863,
        "R2": 0.9679
      }
    }
  }
}